{
  "Arabic": "ar",
  "Bengali": "bn",
  "Bulgarian": "bg",
  "Catalan": "ca",
  "Chinese (Simplified)": "zh-CN",
  "Croatian": "hr",
  "Czech": "cs",
  "Danish": "da",
  "Dutch": "nl",
  "English": "en",
  "Estonian": "et",
  "Finnish": "fi",
  "French": "fr",
  "German": "de",
  "Greek": "el",
  "Gujarati": "gu",
  "Hebrew": "he",
  "Hindi": "hi",
  "Hungarian": "hu",
  "Icelandic": "is",
  "Indonesian": "id",
  "Italian": "it",
  "Japanese": "ja",
  "Kannada": "kn",
  "Korean": "ko",
  "Latvian": "lv",
  "Lithuanian": "lt",
  "Malayalam": "ml",
  "Marathi": "mr",
  "Norwegian": "no",
  "Persian": "fa",
  "Polish": "pl",
  "Portuguese": "pt",
  "Punjabi": "pa",
  "Romanian": "ro",
  "Russian": "ru",
  "Slovak": "sk",
  "Slovenian": "sl",
  "Spanish": "es",
  "Swahili": "sw",
  "Swedish": "sv",
  "Tamil": "ta",
  "Telugu": "te",
  "Thai": "th",
  "Turkish": "tr",
  "Ukrainian": "uk",
  "Urdu": "ur",
  "Vietnamese": "vi",
  "Zulu": "zu"
}
